solana/blockhash.py
solana/keypair.py
solana/message.py
solana/publickey.py
solana/system_program.py
solana/transaction.py
solana_publickey-0.2.1.dist-info/METADATA
solana_publickey-0.2.1.dist-info/WHEEL
solana_publickey-0.2.1.dist-info/top_level.txt
solana_publickey-0.2.1.dist-info/RECORD
